django_pgwatch/__init__.py
django_pgwatch/admin.py
django_pgwatch/apps.py
django_pgwatch/consumer.py
django_pgwatch/examples.py
django_pgwatch/models.py
django_pgwatch/utils.py
django_pgwatch/management/__init__.py
django_pgwatch/management/commands/__init__.py
django_pgwatch/management/commands/pgwatch_cleanup.py
django_pgwatch/management/commands/pgwatch_listen.py
django_pgwatch/migrations/0001_initial.py
django_pgwatch/migrations/0002_install_pg_functions.py
django_pgwatch/migrations/__init__.py
django_pgwatch-1.0.0.dist-info/licenses/LICENSE
django_pgwatch-1.0.0.dist-info/METADATA
django_pgwatch-1.0.0.dist-info/WHEEL
django_pgwatch-1.0.0.dist-info/top_level.txt
django_pgwatch-1.0.0.dist-info/RECORD
