Metadata-Version: 2.4
Name: django-pgwatch
Version: 1.0.0
Summary: Django app for PostgreSQL LISTEN/NOTIFY with persistence and playback
Author-email: Ed Menendez <ed@edmenendez.com>
License: MIT
Project-URL: Homepage, https://github.com/edmenendez/django-pgwatch
Project-URL: Documentation, https://github.com/edmenendez/django-pgwatch#readme
Project-URL: Repository, https://github.com/edmenendez/django-pgwatch
Project-URL: Bug Tracker, https://github.com/edmenendez/django-pgwatch/issues
Keywords: django,postgresql,notify,listen,database,triggers
Classifier: Development Status :: 5 - Production/Stable
Classifier: Intended Audience :: Developers
Classifier: License :: OSI Approved :: MIT License
Classifier: Operating System :: OS Independent
Classifier: Programming Language :: Python :: 3
Classifier: Programming Language :: Python :: 3.9
Classifier: Programming Language :: Python :: 3.10
Classifier: Programming Language :: Python :: 3.11
Classifier: Programming Language :: Python :: 3.12
Classifier: Framework :: Django
Classifier: Framework :: Django :: 4.2
Classifier: Framework :: Django :: 5.0
Classifier: Framework :: Django :: 5.1
Classifier: Topic :: Database
Classifier: Topic :: Software Development :: Libraries :: Python Modules
Requires-Python: >=3.9
License-File: LICENSE
Requires-Dist: Django>=4.2
Requires-Dist: psycopg>=3.0
Provides-Extra: dev
Requires-Dist: pytest>=7.0; extra == "dev"
Requires-Dist: pytest-django>=4.5; extra == "dev"
Requires-Dist: pytest-cov>=4.0; extra == "dev"
Requires-Dist: ruff>=0.1; extra == "dev"
Requires-Dist: mypy>=1.0; extra == "dev"
Requires-Dist: django-stubs>=4.2; extra == "dev"
Dynamic: license-file
